{
  "todos": [
    {
      "id": "d3f6",
      "title": "sdkljfklsdjdsfo",
      "completed": true
    },
    {
      "id": "8529",
      "title": "ldsklfjkdjf",
      "completed": true
    },
    {
      "id": "0b58",
      "title": "we are the ",
      "completed": true
    },
    {
      "id": "093e",
      "title": "sdlijfdjf",
      "completed": true
    },
    {
      "id": "c256",
      "title": "mohsin raza",
      "completed": true
    },
    {
      "id": "913c",
      "title": "d,kfjkldjfkljsdklfj",
      "completed": true
    },
    {
      "id": "3d4d",
      "title": "dlfkdskfsdlkflkfksdf",
      "completed": false
    }
  ]
}